Metadata-Version: 1.0
Name: guessthenumbergame
Version: 0.1
Summary: Guess the number game
Home-page: UNKNOWN
Author: UNKNOWN
Author-email: UNKNOWN
License: UNKNOWN
Platform: UNKNOWN
